{
  "btm": "បន្ទាយមានជ័យ",
  "btb": "បាត់ដំបង",
  "kpc": "កំពង់ចាម",
  "kpch": "កំពង់ឆ្នាំង",
  "kpsp": "កំពង់ស្ពឺ",
  "kpt": "កំពង់ធំ",
  "kp": "កំពត",
  "kdl": "កណ្ដាល",
  "kk": "កោះកុង",
  "kt": "ក្រចេះ",
  "mdk": "មណ្ឌលគិរី",
  "pp": "ភ្នំពេញ",
  "pvh": "ព្រះវិហារ",
  "pv": "ព្រៃវែង",
  "ps": "ពោធិ៍សាត់",
  "rtk": "រតនគិរី",
  "sr": "សៀមរាប",
  "psh": "ព្រះសីហនុ",
  "str": "ស្ទឹងត្រែង",
  "svr": "ស្វាយរៀង",
  "tk": "តាកែវ",
  "omc": "ឧត្ដរមានជ័យ",
  "kep": "កែប",
  "pl": "ប៉ៃលិន",
  "tbk": "ត្បូងឃ្មុំ",
  "mkb": "មង្គលបូរី",
  "phs": "ភ្នំស្រុក",
  "pnp": "ព្រះនេត្រព្រះ",
  "ocv": "អូរជ្រៅ",
  "ssp": "សិរីសោភ័ណ",
  "tp": "ថ្មពួក",
  "svc": "ស្វាយចេក",
  "ml": "ម៉ាឡៃ",
  "ppt": "ប៉ោយប៉ែត",
  "bn": "បាណន់",
  "tmk": "ថ្មគោល",
  "bv": "បវេល",
  "akp": "ឯកភ្នំ",
  "mrs": "មោងឫស្សី",
  "rtm": "រតនមណ្ឌល",
  "sk": "សង្កែ",
  "sl": "សំឡូត",
  "spl": "សំពៅលូន",
  "php": "ភ្នំព្រឹក",
  "kr": "កំរៀង",
  "kkl": "គាស់ក្រឡ",
  "rkr": "រុក្ខគិរី",
  "bt": "បាធាយ",
  "ckl": "ចំការលើ",
  "cp": "ជើងព្រៃ",
  "kpsi": "កំពង់សៀម",
  "kgm": "កងមាស",
  "kst": "កោះសូទិន",
  "pyc": "ព្រៃឈរ",
  "sst": "ស្រីសន្ធរ",
  "brb": "បរិបូណ៌",
  "ckr": "ជលគីរី",
  "kpl": "កំពង់លែង",
  "kptl": "កំពង់ត្រឡាច",
  "rlb": "រលាប្អៀរ",
  "smc": "សាមគ្គីមានជ័យ",
  "tkp": "ទឹកផុស",
  "bsd": "បរសេដ្ឋ",
  "cbm": "ច្បារមន",
  "kps": "គងពិសី",
  "aor": "ឱរ៉ាល់",
  "odk": "ឧដុង្គ",
  "phsr": "ភ្នំស្រួច",
  "srt": "សំរោងទង",
  "thp": "ថ្ពង",
  "bry": "បារាយណ៍",
  "kpsy": "កំពង់ស្វាយ",
  "sts": "ស្ទឹងសែន",
  "psbl": "ប្រាសាទបល្ល័ង្គ",
  "pssb": "ប្រាសាទសំបូរ",
  "snd": "សណ្ដាន់",
  "snt": "សន្ទុក",
  "stg": "ស្ទោង",
  "tgk": "តាំងគោក",
  "akc": "អង្គរជ័យ",
  "btme": "បន្ទាយមាស",
  "cuk": "ឈូក",
  "chk": "ជុំគិរី",
  "dgt": "ដងទង់",
  "kptr": "កំពង់ត្រាច",
  "tkc": "ទឹកឈូ",
  "bk": "បូកគោ",
  "kds": "កណ្ដាលស្ទឹង",
  "kns": "កៀនស្វាយ",
  "kskd": "ខ្សាច់កណ្ដាល",
  "kot": "កោះធំ",
  "lkd": "លើកដែក",
  "lva": "ល្វាឯម",
  "mkp": "មុខកំពូល",
  "aks": "អង្គស្នួល",
  "phl": "ពញាឮ",
  "sang": "ស្អាង",
  "tkm": "តាខ្មៅ",
  "btsk": "បុទុមសាគរ",
  "krsk": "គិរីសាគរ",
  "krpm": "ខេមរភូមិន្ទ",
  "mdsm": "មណ្ឌលសីមា",
  "smb": "ស្រែ អំបិល",
  "tmb": "ថ្មបាំង",
  "chl": "ឆ្លូង",
  "pps": "ព្រែកប្រសព្វ",
  "sbr": "សំបូរ",
  "snl": "ស្នួល",
  "cbr": "ចិត្របុរី",
  "ksm": "កែវសីមា",
  "knh": "កោះញែក",
  "ourg": "អូររាំង",
  "pcd": "ពេជ្រាដា",
  "smnr": "សែនមនោរម្យ",
  "ckm": "ចំការមន",
  "dph": "ដូនពេញ",
  "pmkk": "៧មករា",
  "tlk": "ទួលគោក",
  "dgk": "ដង្កោ",
  "mcy": "មានជ័យ",
  "rsk": "ឫស្សីកែវ",
  "ssk": "សែនសុខ",
  "psc": "ពោធិ៍សែនជ័យ",
  "ccv": "ជ្រោយចង្វារ",
  "pkp": "ព្រែកព្នៅ",
  "cba": "ច្បារអំពៅ",
  "bkk": "បឹងកេងកង",
  "kbl": "កំបូល",
  "cys": "ជ័យសែន",
  "chb": "ឆែប",
  "chks": "ជាំក្សាន្ដ",
  "kul": "គូលែន",
  "rov": "រវៀង",
  "skt": "សង្គមថ្មី",
  "tbmc": "ត្បែងមានជ័យ",
  "bph": "បាភ្នំ",
  "kcm": "កំចាយមារ",
  "kptb": "កំពង់ត្របែក",
  "kchr": "កញ្ជ្រៀច",
  "mes": "មេសាង",
  "pmc": "ពាមជរ",
  "pmr": "ពាមរក៍",
  "per": "ពារាំង",
  "psd": "ព្រះស្ដេច",
  "pur": "ពោធិ៍រៀង",
  "stkd": "ស៊ីធរកណ្ដាល",
  "svat": "ស្វាយអន្ទរ",
  "bak": "បាកាន",
  "kdg": "កណ្ដៀង",
  "krk": "ក្រគរ",
  "pkv": "ភ្នំក្រវ៉ាញ",
  "vlv": "វាលវែង",
  "tlsc": "តាលោសែនជ័យ",
  "adm": "អណ្ដូងមាស",
  "bnl": "បានលុង",
  "brk": "បរកែវ",
  "knm": "កូនមុំ",
  "lpt": "លំផាត់",
  "ochm": "អូរជុំ",
  "oyd": "អូរយ៉ាដាវ",
  "tvg": "តាវែង",
  "vns": "វើនសៃ",
  "akch": "អង្គរជុំ",
  "akth": "អង្គរធំ",
  "bts": "បន្ទាយស្រី",
  "chkg": "ជីក្រែង",
  "krl": "ក្រឡាញ់",
  "puok": "ពួក",
  "psbk": "ប្រាសាទបាគង",
  "snk": "សូទ្រនិគម",
  "srsm": "ស្រីស្នំ",
  "svl": "ស្វាយលើ",
  "vrn": "វ៉ារិន",
  "pyn": "ព្រៃនប់",
  "sth": "ស្ទឹងហាវ",
  "kpsl": "កំពង់សីលា",
  "khru": "កោះរ៉ុង",
  "sesan": "សេសាន",
  "smbk": "សៀមបូក",
  "smpg": "សៀមប៉ាង",
  "tlbv": "ថាឡាបរិវ៉ាត់",
  "bross": "បុរីអូរស្វាយសែនជ័យ",
  "cntr": "ចន្ទ្រា",
  "kpr": "កំពង់រោទិ៍",
  "rmdl": "រំដួល",
  "rmhk": "រមាសហែក",
  "svch": "ស្វាយជ្រំ",
  "svt": "ស្វាយទាប",
  "bvt": "បាវិត",
  "akbr": "អង្គរបូរី",
  "bati": "បាទី",
  "brcs": "បូរីជលសារ",
  "krv": "គីរីវង់",
  "kad": "កោះអណ្ដែត",
  "pykb": "ព្រៃកប្បាស",
  "smr": "សំរោង",
  "dkv": "ដូនកែវ",
  "trmk": "ត្រាំកក់",
  "trg": "ទ្រាំង",
  "alv": "អន្លង់វែង",
  "btap": "បន្ទាយអំពិល",
  "chkl": "ចុងកាល់",
  "tpps": "ត្រពាំងប្រាសាទ",
  "dnca": "ដំណាក់ចង្អើរ",
  "slk": "សាលាក្រៅ",
  "dmb": "តំបែរ",
  "krcm": "ក្រូចឆ្មារ",
  "memot": "មេមត់",
  "orv": "អូររាំងឪ",
  "phk": "ពញាក្រែក",
  "sug": "សួង"
}