{
  "btm": "Banteay Meanchey",
  "btb": "Battambang",
  "kpc": "Kampong Cham",
  "kpch": "Kampong Chhnang",
  "kpsp": "Kampong Speu",
  "kpt": "Kampong Thom",
  "kp": "Kampot",
  "kdl": "Kandal",
  "kk": "Koh Kong",
  "kt": "Kratie",
  "mdk": "Mondul Kiri",
  "pp": "Phnom Penh",
  "pvh": "Preah Vihear",
  "pv": "Prey Veng",
  "ps": "Pursat",
  "rtk": "Ratanak Kiri",
  "sr": "Siemreap",
  "psh": "Preah Sihanouk",
  "str": "Stung Treng",
  "svr": "Svay Rieng",
  "tk": "Takeo",
  "omc": "Oddar Meanchey",
  "kep": "Kep",
  "pl": "Pailin",
  "tbk": "Tboung Khmum",
  "mkb": "Mongkol Borei",
  "phs": "Phnum Srok",
  "pnp": "Preah Netr Preah",
  "ocv": "Ou Chrov",
  "ssp": "Serei Saophoan",
  "tp": "Thma Puok",
  "svc": "Svay Chek",
  "ml": "Malai",
  "ppt": "Poi Pet",
  "bn": "Banan",
  "tmk": "Thma Koul",
  "bv": "Bavel",
  "akp": "Aek Phnum",
  "mrs": "Moung Ruessei",
  "rtm": "Rotonak Mondol",
  "sk": "Sangkae",
  "sl": "Samlout",
  "spl": "Sampov Lun",
  "php": "Phnum Proek",
  "kr": "Kamrieng",
  "kkl": "Koas Krala",
  "rkr": "Rukh Kiri",
  "bt": "Batheay",
  "ckl": "Chamkar Leu",
  "cp": "Cheung Prey",
  "kpsi": "Kampong Siem",
  "kgm": "Kang Meas",
  "kst": "Kaoh Soutin",
  "pyc": "Prey Chhor",
  "sst": "Srei Santhor",
  "brb": "Baribour",
  "ckr": "Chol Kiri",
  "kpl": "Kampong Leaeng",
  "kptl": "Kampong Tralach",
  "rlb": "Rolea B'ier",
  "smc": "Sameakki Mean Chey",
  "tkp": "Tuek Phos",
  "bsd": "Basedth",
  "cbm": "Chbar Mon",
  "kps": "Kong Pisei",
  "aor": "Aoral",
  "odk": "Odongk",
  "phsr": "Phnum Sruoch",
  "srt": "Samraong Tong",
  "thp": "Thpong",
  "bry": "Baray",
  "kpsy": "Kampong Svay",
  "sts": "Stueng Saen",
  "psbl": "Prasat Ballangk",
  "pssb": "Prasat Sambour",
  "snd": "Sandan",
  "snt": "Santuk",
  "stg": "Stoung",
  "tgk": "Taing Kouk",
  "akc": "Angkor Chey",
  "btme": "Banteay Meas",
  "cuk": "Chhuk",
  "chk": "Chum Kiri",
  "dgt": "Dang Tong",
  "kptr": "Kampong Trach",
  "tkc": "Tuek Chhou",
  "bk": "Bokor",
  "kds": "Kandal Stueng",
  "kns": "Kien Svay",
  "kskd": "Khsach Kandal",
  "kot": "Kaoh Thum",
  "lkd": "Leuk Daek",
  "lva": "Lvea Aem",
  "mkp": "Mukh Kampul",
  "aks": "Angk Snuol",
  "phl": "Ponhea Lueu",
  "sang": "S'ang",
  "tkm": "Ta Khmau",
  "btsk": "Botum Sakor",
  "krsk": "Kiri Sakor",
  "krpm": "Khemara Phoumin",
  "mdsm": "Mondol Seima",
  "smb": "Srae Ambel",
  "tmb": "Thma Bang",
  "chl": "Chhloung",
  "pps": "Prek Prasab",
  "sbr": "Sambour",
  "snl": "Snuol",
  "cbr": "Chetr Borei",
  "ksm": "Kaev Seima",
  "knh": "Kaoh Nheaek",
  "ourg": "Ou Reang",
  "pcd": "Pech Chreada",
  "smnr": "Saen Monourom",
  "ckm": "Chamkar Mon",
  "dph": "Doun Penh",
  "pmkk": "Prampir Meakkakra",
  "tlk": "Tuol Kouk",
  "dgk": "Dangkao",
  "mcy": "Mean Chey",
  "rsk": "Russey Keo",
  "ssk": "Saensokh",
  "psc": "Pur SenChey",
  "ccv": "Chraoy Chongvar",
  "pkp": "Praek Pnov",
  "cba": "Chbar Ampov",
  "bkk": "Boeng Keng Kang",
  "kbl": "Kamboul",
  "cys": "Chey Saen",
  "chb": "Chhaeb",
  "chks": "Choam Ksant",
  "kul": "Kuleaen",
  "rov": "Rovieng",
  "skt": "Sangkum Thmei",
  "tbmc": "Tbaeng Mean Chey",
  "bph": "Ba Phnum",
  "kcm": "Kamchay Mear",
  "kptb": "Kampong Trabaek",
  "kchr": "Kanhchriech",
  "mes": "Me Sang",
  "pmc": "Peam Chor",
  "pmr": "Peam Ro",
  "per": "Pea Reang",
  "psd": "Preah Sdach",
  "pur": "Pur Rieng",
  "stkd": "Sithor Kandal",
  "svat": "Svay Antor",
  "bak": "Bakan",
  "kdg": "Kandieng",
  "krk": "Krakor",
  "pkv": "Phnum Kravanh",
  "vlv": "Veal Veaeng",
  "tlsc": "Ta Lou Senchey",
  "adm": "Andoung Meas",
  "bnl": "Ban Lung",
  "brk": "Bar Kaev",
  "knm": "Koun Mom",
  "lpt": "Lumphat",
  "ochm": "Ou Chum",
  "oyd": "Ou Ya Dav",
  "tvg": "Ta Veaeng",
  "vns": "Veun Sai",
  "akch": "Angkor Chum",
  "akth": "Angkor Thum",
  "bts": "Banteay Srei",
  "chkg": "Chi Kraeng",
  "krl": "Kralanh",
  "puok": "Puok",
  "psbk": "Prasat Bakong",
  "snk": "Soutr Nikom",
  "srsm": "Srei Snam",
  "svl": "Svay Leu",
  "vrn": "Varin",
  "pyn": "Prey Nob",
  "sth": "Stueng Hav",
  "kpsl": "Kampong Seila",
  "khru": "Kaoh Rung",
  "sesan": "Sesan",
  "smbk": "Siem Bouk",
  "smpg": "Siem Pang",
  "tlbv": "Thala Barivat",
  "bross": "Borei Ou Svay Senchey",
  "cntr": "Chantrea",
  "kpr": "Kampong Rou",
  "rmdl": "Rumduol",
  "rmhk": "Romeas Haek",
  "svch": "Svay Chrum",
  "svt": "Svay Teab",
  "bvt": "Bavet",
  "akbr": "Angkor Borei",
  "bati": "Bati",
  "brcs": "Borei Cholsar",
  "krv": "Kiri Vong",
  "kad": "Kaoh Andaet",
  "pykb": "Prey Kabbas",
  "smr": "Samraong",
  "dkv": "Doun Kaev",
  "trmk": "Tram Kak",
  "trg": "Treang",
  "alv": "Anlong Veaeng",
  "btap": "Banteay Ampil",
  "chkl": "Chong Kal",
  "tpps": "Trapeang Prasat",
  "dnca": "Damnak Chang'aeur",
  "slk": "Sala Krau",
  "dmb": "Dambae",
  "krcm": "Krouch Chhmar",
  "memot": "Memot",
  "orv": "Ou Reang Ov",
  "phk": "Ponhea Kraek",
  "sug": "Suong"
}