[{"id":"937bdfc5-b4bc-49b8-a769-7f0d7c1a207c","name":"គ្លីនិកទី 1","addresses":"ផ្ទះលេខ22 ផ្លូវ87 ឃុំផ្លូវទូក ស្រុកកំពង់លែង ខេត្តកំពង់ឆ្នាំង","province_id":"04","district_id":"0404","commune_id":"040404","street":"87","house_number":"22","tels":["098765432"],"emails":[],"websites":[],"facebook_pages":[],"telegram_username":null,"description":null,"latitude":null,"longitude":null,"services":["សម្ភព និងរោគស្ត្រី"],"updated_at":"2023-03-02T00:00:19.548+07:00","service_ids":["45f97469-0670-4ffe-87f3-dacb178ce67b"],"tags":["សម្ភព និងរោគស្ត្រី"],"logo":null,"working_days":[{"day":"monday","open":true,"working_hours":[{"open_at":8,"close_at":17}]},{"day":"tuesday","open":true,"working_hours":[{"open_at":8,"close_at":17}]},{"day":"wednesday","open":false,"working_hours":[]},{"day":"thursday","open":false,"working_hours":[]},{"day":"friday","open":false,"working_hours":[]},{"day":"saturday","open":false,"working_hours":[]},{"day":"sunday","open":false,"working_hours":[]}]},{"id":"2a333f37-6d64-4f52-9c3b-8d79e2bc895e","name":"គ្លីនិកទី 2","addresses":"ផ្ទះលេខ98 ផ្លូវ76 ឃុំក្រយា ស្រុកប្រាសាទបល្ល័ង្គ ខេត្តកំពង់ធំ","province_id":"06","district_id":"0604","commune_id":"060402","street":"76","house_number":"98","tels":["012345678"],"emails":[],"websites":[],"facebook_pages":[],"telegram_username":null,"description":null,"latitude":null,"longitude":null,"services":["សុខភាពបន្តពូជ"],"updated_at":"2023-03-02T13:29:25.518+07:00","service_ids":["265524bc-e15d-4ad1-96ff-aba74fb02907"],"tags":["សុខភាពបន្តពូជ"],"logo":"/uploads/facility/logo/2a333f37-6d64-4f52-9c3b-8d79e2bc895e/marie_stopes.png","working_days":[{"day":"monday","open":true,"working_hours":[{"open_at":8,"close_at":17}]},{"day":"tuesday","open":true,"working_hours":[{"open_at":8,"close_at":17}]},{"day":"wednesday","open":false,"working_hours":[]},{"day":"thursday","open":false,"working_hours":[]},{"day":"friday","open":false,"working_hours":[]},{"day":"saturday","open":false,"working_hours":[]},{"day":"sunday","open":false,"working_hours":[]}]},{"id":"6134313e-2608-48ac-8c65-1cf85bb906b1","name":"គ្លីនិកទី​ 3","addresses":"ផ្ទះលេខ20E ផ្លូវ110 ឃុំដំរីផុង ស្រុកឆ្លូង ខេត្តក្រចេះ","province_id":"10","district_id":"1001","commune_id":"100102","street":"110","house_number":"20E","tels":["089765432"],"emails":[],"websites":[],"facebook_pages":[],"telegram_username":null,"description":null,"latitude":null,"longitude":null,"services":["ជំងឺមហារីក"],"updated_at":"2023-03-02T00:05:55.370+07:00","service_ids":["89d4deed-ef10-41b6-a68c-57a0d797db3a"],"tags":["ជំងឺមហារីក"],"logo":"/uploads/facility/logo/6134313e-2608-48ac-8c65-1cf85bb906b1/rhac_logo.jpeg","working_days":[{"day":"monday","open":true,"working_hours":[{"open_at":8,"close_at":17}]},{"day":"tuesday","open":true,"working_hours":[{"open_at":8,"close_at":17}]},{"day":"wednesday","open":false,"working_hours":[]},{"day":"thursday","open":false,"working_hours":[]},{"day":"friday","open":false,"working_hours":[]},{"day":"saturday","open":false,"working_hours":[]},{"day":"sunday","open":false,"working_hours":[]}]},{"id":"3edf536f-8b37-4fc9-b823-59ed99e0d295","name":"គ្លីនិកទី 4","addresses":"ផ្ទះលេខ34 ផ្លូវ56 សង្កាត់ស្ពានថ្ម ខណ្ឌដង្កោ រាជធានីភ្នំពេញ","province_id":"12","district_id":"1205","commune_id":"120519","street":"56","house_number":"34","tels":["012432234"],"emails":[],"websites":[],"facebook_pages":[],"telegram_username":null,"description":null,"latitude":null,"longitude":null,"services":["សម្ភព និងរោគស្ត្រី","សុខភាពបន្តពូជ"],"updated_at":"2023-03-02T00:07:32.900+07:00","service_ids":["45f97469-0670-4ffe-87f3-dacb178ce67b","38e2942b-804a-4f3a-87a1-beb65c8abefe"],"tags":["សម្ភព និងរោគស្ត្រី","សុខភាពបន្តពូជ"],"logo":"/uploads/facility/logo/3edf536f-8b37-4fc9-b823-59ed99e0d295/rhac_logo.jpeg","working_days":[{"day":"monday","open":true,"working_hours":[{"open_at":8,"close_at":17}]},{"day":"tuesday","open":true,"working_hours":[{"open_at":8,"close_at":17}]},{"day":"wednesday","open":false,"working_hours":[]},{"day":"thursday","open":false,"working_hours":[]},{"day":"friday","open":false,"working_hours":[]},{"day":"saturday","open":false,"working_hours":[]},{"day":"sunday","open":false,"working_hours":[]}]},{"id":"336a28f3-c500-4759-80e9-6badaeeb3bee","name":"គ្លីនិកទី 5","addresses":"ផ្ទះលេខ110 ផ្លូវ320 សង្កាត់ចំការសំរោង ក្រុងបាត់ដំបង ខេត្តបាត់ដំបង","province_id":"02","district_id":"0203","commune_id":"020304","street":"320","house_number":"110","tels":["014321123"],"emails":[],"websites":[],"facebook_pages":[],"telegram_username":null,"description":null,"latitude":null,"longitude":null,"services":["សុខភាពកុមារ"],"updated_at":"2023-03-02T00:09:14.953+07:00","service_ids":["8d9c104e-fb14-4537-853a-365203fe3a81"],"tags":["សុខភាពកុមារ"],"logo":"/uploads/facility/logo/336a28f3-c500-4759-80e9-6badaeeb3bee/marie_stopes_logo.png","working_days":[{"day":"monday","open":true,"working_hours":[{"open_at":8,"close_at":17}]},{"day":"tuesday","open":true,"working_hours":[{"open_at":8,"close_at":17}]},{"day":"wednesday","open":false,"working_hours":[]},{"day":"thursday","open":false,"working_hours":[]},{"day":"friday","open":false,"working_hours":[]},{"day":"saturday","open":false,"working_hours":[]},{"day":"sunday","open":false,"working_hours":[]}]},{"id":"769e66c3-6b71-4c96-8fbb-4f3fdad4e245","name":"គ្លីនិកទី 6","addresses":"ផ្ទះលេខ10 ផ្លូវ87 ឃុំជប់វារី ស្រុកព្រះនេត្រព្រះ ខេត្តបន្ទាយមានជ័យ","province_id":"01","district_id":"0104","commune_id":"010402","street":"87","house_number":"10","tels":["087654564"],"emails":[],"websites":[],"facebook_pages":[],"telegram_username":null,"description":null,"latitude":null,"longitude":null,"services":["ជំងឺសើស្បែក និងកាមរោគ"],"updated_at":"2023-03-02T00:12:04.982+07:00","service_ids":["55b1c9c8-ad3f-4f11-8bd0-0a04ea973ce1"],"tags":["ជំងឺសើស្បែក និងកាមរោគ"],"logo":"/uploads/facility/logo/769e66c3-6b71-4c96-8fbb-4f3fdad4e245/rhac_logo.jpeg","working_days":[{"day":"monday","open":true,"working_hours":[{"open_at":8,"close_at":17}]},{"day":"tuesday","open":true,"working_hours":[{"open_at":8,"close_at":17}]},{"day":"wednesday","open":false,"working_hours":[]},{"day":"thursday","open":false,"working_hours":[]},{"day":"friday","open":false,"working_hours":[]},{"day":"saturday","open":false,"working_hours":[]},{"day":"sunday","open":false,"working_hours":[]}]},{"id":"db964455-149c-4ace-9039-261750ced66c","name":"គ្លីនិកទី 7","addresses":"ផ្ទះលេខ8 ផ្លូវ75 ឃុំជើងរាស់ ស្រុកឧដុង្គ ខេត្តកំពង់ស្ពឺ","province_id":"05","district_id":"0505","commune_id":"050502","street":"75","house_number":"8","tels":["099876678"],"emails":[],"websites":[],"facebook_pages":[],"telegram_username":null,"description":null,"latitude":null,"longitude":null,"services":["សុខភាពផ្លូវភេទ"],"updated_at":"2023-03-02T00:11:44.901+07:00","service_ids":["155864e5-752c-408f-9c9a-36efabc8b43e"],"tags":["សុខភាពផ្លូវភេទ"],"logo":"/uploads/facility/logo/db964455-149c-4ace-9039-261750ced66c/marie_stopes_logo.png","working_days":[{"day":"monday","open":true,"working_hours":[{"open_at":8,"close_at":17}]},{"day":"tuesday","open":true,"working_hours":[{"open_at":8,"close_at":17}]},{"day":"wednesday","open":false,"working_hours":[]},{"day":"thursday","open":false,"working_hours":[]},{"day":"friday","open":false,"working_hours":[]},{"day":"saturday","open":false,"working_hours":[]},{"day":"sunday","open":false,"working_hours":[]}]},{"id":"080db2a5-97cb-4e2c-a011-c8487faf9410","name":"គ្លីនិកទី 8","addresses":"ផ្ទះលេខ87 ផ្លូវ435 ឃុំជីផុច ស្រុកមេសាង ខេត្តព្រៃវែង","province_id":"14","district_id":"1405","commune_id":"140503","street":"435","house_number":"87","tels":["077765567"],"emails":[],"websites":[],"facebook_pages":[],"telegram_username":null,"description":null,"latitude":null,"longitude":null,"services":["ពិនិត្យឈាម"],"updated_at":"2023-03-02T00:13:33.863+07:00","service_ids":["ad17b076-24ab-45d6-9da7-2db588f5e8d9"],"tags":["ពិនិត្យឈាម"],"logo":"/uploads/facility/logo/080db2a5-97cb-4e2c-a011-c8487faf9410/rhac_logo.jpeg","working_days":[{"day":"monday","open":true,"working_hours":[{"open_at":8,"close_at":17}]},{"day":"tuesday","open":true,"working_hours":[{"open_at":8,"close_at":17}]},{"day":"wednesday","open":false,"working_hours":[]},{"day":"thursday","open":false,"working_hours":[]},{"day":"friday","open":false,"working_hours":[]},{"day":"saturday","open":false,"working_hours":[]},{"day":"sunday","open":false,"working_hours":[]}]},{"id":"fe903613-5229-48c4-b2e3-783821e9fd0b","name":"គ្លីនិកទី 9","addresses":"ផ្ទះលេខ56 ផ្លូវ87 សង្កាត់អូរឫស្សីទី ៤ ខណ្ឌ៧មករា រាជធានីភ្នំពេញ","province_id":"12","district_id":"1203","commune_id":"120304","street":"87","house_number":"56","tels":["099876678"],"emails":[],"websites":[],"facebook_pages":[],"telegram_username":null,"description":null,"latitude":null,"longitude":null,"services":["សុខភាពផ្លូវភេទ","សម្ភព និងរោគស្ត្រី"],"updated_at":"2023-03-02T00:15:54.072+07:00","service_ids":["155864e5-752c-408f-9c9a-36efabc8b43e","45f97469-0670-4ffe-87f3-dacb178ce67b"],"tags":["សុខភាពផ្លូវភេទ","សម្ភព និងរោគស្ត្រី"],"logo":"/uploads/facility/logo/fe903613-5229-48c4-b2e3-783821e9fd0b/marie_stopes_logo.png","working_days":[{"day":"monday","open":true,"working_hours":[{"open_at":8,"close_at":17}]},{"day":"tuesday","open":true,"working_hours":[{"open_at":8,"close_at":17}]},{"day":"wednesday","open":false,"working_hours":[]},{"day":"thursday","open":false,"working_hours":[]},{"day":"friday","open":false,"working_hours":[]},{"day":"saturday","open":false,"working_hours":[]},{"day":"sunday","open":false,"working_hours":[]}]},{"id":"32582468-1522-42de-a509-de47627079ee","name":"គ្លីនិកទី 10","addresses":"ផ្ទះលេខ100 ផ្លូវ97 ឃុំនរា ស្រុកសង្កែ ខេត្តបាត់ដំបង","province_id":"02","district_id":"0208","commune_id":"020802","street":"97","house_number":"100","tels":["096543345"],"emails":[],"websites":[],"facebook_pages":[],"telegram_username":null,"description":null,"latitude":null,"longitude":null,"services":["សុខភាពកុមារ","សម្ភព និងរោគស្ត្រី"],"updated_at":"2023-03-02T00:17:17.745+07:00","service_ids":["c13d51e0-10ce-47d6-8e88-c605a4b585f4","c8d29ea4-ad07-43af-9f0b-323c12664a04"],"tags":["សុខភាពកុមារ","សម្ភព និងរោគស្ត្រី"],"logo":"/uploads/facility/logo/32582468-1522-42de-a509-de47627079ee/rhac_logo.jpeg","working_days":[{"day":"monday","open":true,"working_hours":[{"open_at":8,"close_at":17}]},{"day":"tuesday","open":true,"working_hours":[{"open_at":8,"close_at":17}]},{"day":"wednesday","open":false,"working_hours":[]},{"day":"thursday","open":false,"working_hours":[]},{"day":"friday","open":false,"working_hours":[]},{"day":"saturday","open":false,"working_hours":[]},{"day":"sunday","open":false,"working_hours":[]}]},{"id":"eecc55c4-0d0d-4c6d-b177-e8b63382f656","name":"គ្លីនិកទី​ 11","addresses":"ផ្ទះលេខ11 ផ្លូវ134 ឃុំកំពង់កុង ស្រុកកោះធំ ខេត្តកណ្ដាល","province_id":"08","district_id":"0804","commune_id":"080403","street":"134","house_number":"11","tels":["013123123"],"emails":[],"websites":[],"facebook_pages":[],"telegram_username":null,"description":null,"latitude":null,"longitude":null,"services":["ជំងឺមហារីក"],"updated_at":"2023-03-02T00:18:37.402+07:00","service_ids":["7b79d594-b836-44df-9618-b374933f79f6"],"tags":["ជំងឺមហារីក"],"logo":"/uploads/facility/logo/eecc55c4-0d0d-4c6d-b177-e8b63382f656/rhac_logo.jpeg","working_days":[{"day":"monday","open":false,"working_hours":[]},{"day":"tuesday","open":true,"working_hours":[{"open_at":8,"close_at":17}]},{"day":"wednesday","open":true,"working_hours":[{"open_at":8,"close_at":17}]},{"day":"thursday","open":false,"working_hours":[]},{"day":"friday","open":false,"working_hours":[]},{"day":"saturday","open":false,"working_hours":[]},{"day":"sunday","open":false,"working_hours":[]}]},{"id":"58a2b5ca-8bf1-4caf-ba63-15e731ddf801","name":"គ្លីនិកទី 12","addresses":"ផ្ទះលេខ12 ផ្លូវ320 ឃុំស្ពឺ ស្រុកចំការលើ ខេត្តកំពង់ចាម","province_id":"03","district_id":"0302","commune_id":"030205","street":"320","house_number":"12","tels":["067123321"],"emails":[],"websites":[],"facebook_pages":[],"telegram_username":null,"description":null,"latitude":null,"longitude":null,"services":["ជំងឺសើស្បែក និងកាមរោគ"],"updated_at":"2023-03-02T00:21:20.644+07:00","service_ids":["55b1c9c8-ad3f-4f11-8bd0-0a04ea973ce1"],"tags":["ជំងឺសើស្បែក និងកាមរោគ"],"logo":"/uploads/facility/logo/58a2b5ca-8bf1-4caf-ba63-15e731ddf801/marie_stopes_logo.png","working_days":[{"day":"monday","open":true,"working_hours":[{"open_at":8,"close_at":17}]},{"day":"tuesday","open":true,"working_hours":[{"open_at":8,"close_at":17}]},{"day":"wednesday","open":false,"working_hours":[]},{"day":"thursday","open":false,"working_hours":[]},{"day":"friday","open":false,"working_hours":[]},{"day":"saturday","open":false,"working_hours":[]},{"day":"sunday","open":false,"working_hours":[]}]},{"id":"919a3255-8516-47a6-bea6-a0fc89f0a686","name":"គ្លីនិកទី 13","addresses":"ផ្ទះលេខ45 ផ្លូវ75 ឃុំកោះស្រឡាយ ស្រុកសៀមបូក ខេត្តស្ទឹងត្រែង","province_id":"19","district_id":"1902","commune_id":"190203","street":"75","house_number":"45","tels":["099789789"],"emails":[],"websites":[],"facebook_pages":[],"telegram_username":null,"description":null,"latitude":null,"longitude":null,"services":[],"updated_at":"2023-03-02T00:21:05.745+07:00","service_ids":[],"tags":["ពិនិត្យឈាម"],"logo":"/uploads/facility/logo/919a3255-8516-47a6-bea6-a0fc89f0a686/marie_stopes_logo.png","working_days":[{"day":"monday","open":true,"working_hours":[{"open_at":8,"close_at":17}]},{"day":"tuesday","open":true,"working_hours":[{"open_at":8,"close_at":17}]},{"day":"wednesday","open":false,"working_hours":[]},{"day":"thursday","open":false,"working_hours":[]},{"day":"friday","open":false,"working_hours":[]},{"day":"saturday","open":false,"working_hours":[]},{"day":"sunday","open":false,"working_hours":[]}]},{"id":"6ad5c745-fdfa-4519-93a5-4f90335bf6fc","name":"គ្លីនិកទី 14","addresses":"ផ្ទះលេខ67 ផ្លូវ90 សង្កាត់ប្អេរ ក្រុងកំពង់ឆ្នាំង ខេត្តកំពង់ឆ្នាំង","province_id":"04","district_id":"0403","commune_id":"040303","street":"90","house_number":"67","tels":["023123321"],"emails":[],"websites":[],"facebook_pages":[],"telegram_username":null,"description":null,"latitude":null,"longitude":null,"services":["រោគបុរស"],"updated_at":"2023-03-02T00:22:45.583+07:00","service_ids":["07d89ea2-7edf-4dd3-b403-7317d07d6fd6"],"tags":["រោគបុរស"],"logo":"/uploads/facility/logo/6ad5c745-fdfa-4519-93a5-4f90335bf6fc/rhac_logo.jpeg","working_days":[{"day":"monday","open":true,"working_hours":[{"open_at":8,"close_at":17}]},{"day":"tuesday","open":true,"working_hours":[{"open_at":8,"close_at":17}]},{"day":"wednesday","open":false,"working_hours":[]},{"day":"thursday","open":false,"working_hours":[]},{"day":"friday","open":false,"working_hours":[]},{"day":"saturday","open":false,"working_hours":[]},{"day":"sunday","open":false,"working_hours":[]}]},{"id":"288e20c1-43bf-40be-b3a2-3546199e7fc1","name":"គ្លីនិកទី 15","addresses":"ផ្ទះលេខ54 ផ្លូវ310 ឃុំកោះស្ដេច ស្រុកគិរីសាគរ ខេត្តកោះកុង","province_id":"09","district_id":"0902","commune_id":"090201","street":"310","house_number":"54","tels":["099567765"],"emails":[],"websites":[],"facebook_pages":[],"telegram_username":null,"description":null,"latitude":null,"longitude":null,"services":["សុខភាពបន្តពូជ","សុខភាពផ្លូវភេទ"],"updated_at":"2023-03-02T00:24:17.922+07:00","service_ids":["265524bc-e15d-4ad1-96ff-aba74fb02907","e14e19bd-98e4-4088-a743-483a5470fe79"],"tags":["សុខភាពផ្លូវភេទ","សុខភាពបន្តពូជ"],"logo":"/uploads/facility/logo/288e20c1-43bf-40be-b3a2-3546199e7fc1/marie_stopes_logo.png","working_days":[{"day":"monday","open":true,"working_hours":[{"open_at":8,"close_at":17}]},{"day":"tuesday","open":true,"working_hours":[{"open_at":8,"close_at":17}]},{"day":"wednesday","open":false,"working_hours":[]},{"day":"thursday","open":false,"working_hours":[]},{"day":"friday","open":false,"working_hours":[]},{"day":"saturday","open":false,"working_hours":[]},{"day":"sunday","open":false,"working_hours":[]}]},{"id":"14b94696-532d-4cac-8761-74dc387c16db","name":"គ្លីនិកទី 16","addresses":"ផ្ទះលេខ32 ផ្លូវ86 ឃុំអ បួនលើ ស្រុកកោះញែក ខេត្តមណ្ឌលគិរី","province_id":"11","district_id":"1102","commune_id":"110202","street":"86","house_number":"32","tels":["077456654"],"emails":[],"websites":[],"facebook_pages":[],"telegram_username":null,"description":null,"latitude":null,"longitude":null,"services":["សុខភាពកុមារ","សម្ភព និងរោគស្ត្រី"],"updated_at":"2023-03-02T00:25:38.299+07:00","service_ids":["edd77c0c-8715-4d25-b47b-ca8cb42bcbb1","ce98fd44-983c-4887-98b2-62ae4349986d"],"tags":["សុខភាពកុមារ","សម្ភព និងរោគស្ត្រី"],"logo":"/uploads/facility/logo/14b94696-532d-4cac-8761-74dc387c16db/rhac_logo.jpeg","working_days":[{"day":"monday","open":true,"working_hours":[{"open_at":8,"close_at":17}]},{"day":"tuesday","open":true,"working_hours":[{"open_at":8,"close_at":17}]},{"day":"wednesday","open":false,"working_hours":[]},{"day":"thursday","open":false,"working_hours":[]},{"day":"friday","open":false,"working_hours":[]},{"day":"saturday","open":false,"working_hours":[]},{"day":"sunday","open":false,"working_hours":[]}]},{"id":"a1bf439b-c352-4fae-a78d-452919dbe1a3","name":"គ្លីនិកទី​ 17","addresses":"ផ្ទះលេខ89 ផ្លូវ65 ឃុំកំពង់ត្រឡាច ស្រុកកំពង់ត្រឡាច ខេត្តកំពង់ឆ្នាំង","province_id":"04","district_id":"0405","commune_id":"040504","street":"65","house_number":"89","tels":["012987789"],"emails":[],"websites":[],"facebook_pages":[],"telegram_username":null,"description":null,"latitude":null,"longitude":null,"services":["ពិនិត្យឈាម","ជំងឺមហារីក"],"updated_at":"2023-03-02T00:27:10.242+07:00","service_ids":["cf26da9d-c9db-4e57-87e0-20b45a0f630a","ec532699-6ab6-41e1-a525-c3cc266e36d4"],"tags":["ពិនិត្យឈាម","ជំងឺមហារីក"],"logo":"/uploads/facility/logo/a1bf439b-c352-4fae-a78d-452919dbe1a3/rhac_logo.jpeg","working_days":[{"day":"monday","open":true,"working_hours":[{"open_at":8,"close_at":17}]},{"day":"tuesday","open":true,"working_hours":[{"open_at":8,"close_at":17}]},{"day":"wednesday","open":false,"working_hours":[]},{"day":"thursday","open":false,"working_hours":[]},{"day":"friday","open":false,"working_hours":[]},{"day":"saturday","open":false,"working_hours":[]},{"day":"sunday","open":false,"working_hours":[]}]},{"id":"5fb62a41-4e2c-4e41-90ac-146d81314870","name":"គ្លីនិកទី 18","addresses":"ផ្ទះលេខ110 ផ្លូវ52 សង្កាត់ចោមចៅទី១ ខណ្ឌពោធិ៍សែនជ័យ រាជធានីភ្នំពេញ","province_id":"12","district_id":"1209","commune_id":"120914","street":"52","house_number":"110","tels":["017456654"],"emails":[],"websites":[],"facebook_pages":[],"telegram_username":null,"description":null,"latitude":null,"longitude":null,"services":["ពិនិត្យអេកូ"],"updated_at":"2023-03-02T00:28:37.330+07:00","service_ids":["558b4d36-da94-47ac-b210-2ecf36c14023"],"tags":["ពិនិត្យអេកូ"],"logo":"/uploads/facility/logo/5fb62a41-4e2c-4e41-90ac-146d81314870/rhac_logo.jpeg","working_days":[{"day":"monday","open":true,"working_hours":[{"open_at":8,"close_at":17}]},{"day":"tuesday","open":true,"working_hours":[{"open_at":8,"close_at":17}]},{"day":"wednesday","open":false,"working_hours":[]},{"day":"thursday","open":false,"working_hours":[]},{"day":"friday","open":false,"working_hours":[]},{"day":"saturday","open":false,"working_hours":[]},{"day":"sunday","open":false,"working_hours":[]}]},{"id":"d19ea178-a75a-48cd-83cd-2c85c52ff61e","name":"គ្លីនិកទី 19","addresses":"ផ្ទះលេខ87 ផ្លូវ433 សង្កាត់សំបួរមាស ក្រុងកំពង់ចាម ខេត្តកំពង់ចាម","province_id":"03","district_id":"0305","commune_id":"030503","street":"433","house_number":"87","tels":["095765567"],"emails":[],"websites":[],"facebook_pages":[],"telegram_username":null,"description":null,"latitude":null,"longitude":null,"services":["សុខភាពផ្លូវភេទ","សុខភាពបន្តពូជ"],"updated_at":"2023-03-02T00:29:57.581+07:00","service_ids":["58daf013-afc6-4899-9f2c-424b1791dd40","2a7318b3-5b48-4379-96d3-e58da90ffd9a"],"tags":["សុខភាពបន្តពូជ","សុខភាពផ្លូវភេទ"],"logo":"/uploads/facility/logo/d19ea178-a75a-48cd-83cd-2c85c52ff61e/marie_stopes_logo.png","working_days":[{"day":"monday","open":true,"working_hours":[{"open_at":8,"close_at":17}]},{"day":"tuesday","open":true,"working_hours":[{"open_at":8,"close_at":17}]},{"day":"wednesday","open":false,"working_hours":[]},{"day":"thursday","open":false,"working_hours":[]},{"day":"friday","open":false,"working_hours":[]},{"day":"saturday","open":false,"working_hours":[]},{"day":"sunday","open":false,"working_hours":[]}]},{"id":"17c2c356-86af-40f1-9e55-5f45143b686f","name":"គ្លីនិកទី 20","addresses":"ផ្ទះលេខ23 ផ្លូវ70 ឃុំព្រីងធំ ស្រុកជាំក្សាន្ដ ខេត្តព្រះវិហារ","province_id":"13","district_id":"1303","commune_id":"130303","street":"70","house_number":"23","tels":["018456654"],"emails":[],"websites":[],"facebook_pages":[],"telegram_username":null,"description":null,"latitude":null,"longitude":null,"services":["ជំងឺទូទៅ"],"updated_at":"2023-03-02T00:31:33.922+07:00","service_ids":["807914ea-0ce4-413c-bf2b-3c341e9094de"],"tags":["ជំងឺទូទៅ"],"logo":"/uploads/facility/logo/17c2c356-86af-40f1-9e55-5f45143b686f/rhac_logo.jpeg","working_days":[{"day":"monday","open":true,"working_hours":[{"open_at":8,"close_at":17}]},{"day":"tuesday","open":true,"working_hours":[{"open_at":8,"close_at":17}]},{"day":"wednesday","open":false,"working_hours":[]},{"day":"thursday","open":false,"working_hours":[]},{"day":"friday","open":false,"working_hours":[]},{"day":"saturday","open":false,"working_hours":[]},{"day":"sunday","open":false,"working_hours":[]}]}]